tests/__init__.py
tests/test_tasks.py
tests/test_views.py
udata_recommendations/__init__.py
udata_recommendations/schema.json
udata_recommendations/settings.py
udata_recommendations/tasks.py
udata_recommendations/views.py
udata_recommendations/templates/dataset-recommendations-externals.html
udata_recommendations/templates/dataset-recommendations-reuses.html
udata_recommendations/templates/dataset-recommendations.html
udata_recommendations/translations/recommendations.pot
udata_recommendations/translations/fr/LC_MESSAGES/recommendations.mo
udata_recommendations/translations/fr/LC_MESSAGES/recommendations.po
udata_recommendations-3.1.7.dist-info/LICENSE
udata_recommendations-3.1.7.dist-info/METADATA
udata_recommendations-3.1.7.dist-info/WHEEL
udata_recommendations-3.1.7.dist-info/entry_points.txt
udata_recommendations-3.1.7.dist-info/top_level.txt
udata_recommendations-3.1.7.dist-info/RECORD
