Metadata-Version: 2.1
Name: udata-recommendations
Version: 3.1.7
Summary: uData content recommendations bridge
Home-page: https://github.com/opendatateam/udata-recommendations
Author: Opendata Team
Author-email: contact@opendata.team
License: LGPL
Keywords: udata recommendations
Classifier: Development Status :: 3 - Alpha
Classifier: Programming Language :: Python
Classifier: Environment :: Web Environment
Classifier: Operating System :: OS Independent
Classifier: Intended Audience :: Developers
Classifier: Topic :: System :: Software Distribution
Classifier: Programming Language :: Python
Classifier: Programming Language :: Python :: 3
Classifier: Programming Language :: Python :: 3.7
Classifier: Topic :: Software Development :: Libraries :: Python Modules
Classifier: License :: OSI Approved :: GNU Library or Lesser General Public License (LGPL)
Requires-Python: >=3.7
License-File: LICENSE
Requires-Dist: udata >=3.2.0
Requires-Dist: udata-front >=3.1.3
Requires-Dist: jsonschema ==4.23.0
Provides-Extra: test
Requires-Dist: mock ==5.2.0 ; extra == 'test'
Requires-Dist: pytest ==7.4.4 ; extra == 'test'
Requires-Dist: pytest-flask ==1.3.0 ; extra == 'test'
Requires-Dist: pytest-mock ==3.14.0 ; extra == 'test'
Requires-Dist: pytest-sugar ==1.0.0 ; extra == 'test'
Requires-Dist: requests-mock ==1.12.1 ; extra == 'test'
